simple_test_generator/__init__.py
simple_test_generator/__main__.py
simple_test_generator/common.py
simple_test_generator/constants.py
simple_test_generator/main.py
simple_test_generator/run_generator.py
simple_test_generator/runtime.py
simple_test_generator-0.27.dist-info/WHEEL
simple_test_generator-0.27.dist-info/METADATA
simple_test_generator-0.27.dist-info/RECORD
