Metadata-Version: 2.1
Name: simple_test_generator
Version: 0.27
Summary: A simple cli-based recorder for Python
Home-page: https://github.com/jeshan/simple-test-generator
License: UNKNOWN
Author: Jeshan G. BABOOA
Author-email: j@jeshan.co
Classifier: License :: OSI Approved :: MIT License
Requires-Dist: jsonpickle <2
Requires-Dist: loguru <1
